gridappsd/__init__.py
gridappsd/__main__.py
gridappsd/app_registration.py
gridappsd/difference_builder.py
gridappsd/docker_handler.py
gridappsd/field_interface/__init__.py
gridappsd/goss.py
gridappsd/gridappsd.py
gridappsd/houses.py
gridappsd/json_extension.py
gridappsd/loghandler.py
gridappsd/register_app.py
gridappsd/simulation.py
gridappsd/timeseries.py
gridappsd/topics.py
gridappsd/utils.py
gridappsd_python-2025.3.1.dist-info/METADATA
gridappsd_python-2025.3.1.dist-info/WHEEL
gridappsd_python-2025.3.1.dist-info/entry_points.txt
gridappsd_python-2025.3.1.dist-info/RECORD
