Metadata-Version: 2.3
Name: gridappsd-python
Version: 2025.3.1
Summary: A GridAPPS-D Python Adapter
License: BSD-3-Clause
Keywords: gridappsd,grid,activemq,powergrid,simulation,library
Author: C. Allwardt
Author-email: 3979063+craig8@users.noreply.github.com
Requires-Python: >=3.10,<4.0
Classifier: License :: OSI Approved :: BSD License
Classifier: Programming Language :: Python :: 3
Classifier: Programming Language :: Python :: 3.10
Classifier: Programming Language :: Python :: 3.11
Classifier: Programming Language :: Python :: 3.12
Classifier: Programming Language :: Python :: 3.13
Requires-Dist: PyYAML (>=6.0,<7.0)
Requires-Dist: dateutils (>=0.6.7,<0.7.0)
Requires-Dist: pytz (>=2022.7,<2023.0)
Requires-Dist: requests (==2.28.2)
Requires-Dist: stomp-py (==6.0.0)
Project-URL: Homepage, https://gridappsd.readthedocs.io
Project-URL: Repository, https://github.com/GRIDAPPSD/gridappsd-python
